bella_domify-0.1.6.8.dist-info/licenses/LICENSE
doc_parser/__init__.py
doc_parser/context.py
doc_parser/dom_parser/__init__.py
doc_parser/dom_parser/domtree/__init__.py
doc_parser/dom_parser/domtree/domtree.py
doc_parser/dom_parser/parsers/__init__.py
doc_parser/dom_parser/parsers/base.py
doc_parser/dom_parser/parsers/excel/__init__.py
doc_parser/dom_parser/parsers/excel/converter.py
doc_parser/dom_parser/parsers/pdf/__init__.py
doc_parser/dom_parser/parsers/pdf/config.py
doc_parser/dom_parser/parsers/pdf/converter.py
doc_parser/dom_parser/parsers/pdf/domtree_parser.py
doc_parser/dom_parser/parsers/pdf/common/Block.py
doc_parser/dom_parser/parsers/pdf/common/Collection.py
doc_parser/dom_parser/parsers/pdf/common/Element.py
doc_parser/dom_parser/parsers/pdf/common/__init__.py
doc_parser/dom_parser/parsers/pdf/common/algorithm.py
doc_parser/dom_parser/parsers/pdf/common/constants.py
doc_parser/dom_parser/parsers/pdf/common/docx.py
doc_parser/dom_parser/parsers/pdf/common/ocr.py
doc_parser/dom_parser/parsers/pdf/common/share.py
doc_parser/dom_parser/parsers/pdf/extend/__init__.py
doc_parser/dom_parser/parsers/pdf/extend/common/BlockExtend.py
doc_parser/dom_parser/parsers/pdf/extend/common/RelationConstruct.py
doc_parser/dom_parser/parsers/pdf/extend/common/__init__.py
doc_parser/dom_parser/parsers/pdf/extend/image/ImageSpanExtend.py
doc_parser/dom_parser/parsers/pdf/extend/image/__init__.py
doc_parser/dom_parser/parsers/pdf/extend/layout/ColumnExtend.py
doc_parser/dom_parser/parsers/pdf/extend/layout/SectionExtend.py
doc_parser/dom_parser/parsers/pdf/extend/layout/SectionsExtend.py
doc_parser/dom_parser/parsers/pdf/extend/layout/__init__.py
doc_parser/dom_parser/parsers/pdf/extend/page/PageExtend.py
doc_parser/dom_parser/parsers/pdf/extend/page/PagesExtend.py
doc_parser/dom_parser/parsers/pdf/extend/page/__init__.py
doc_parser/dom_parser/parsers/pdf/extend/table/CellExtend.py
doc_parser/dom_parser/parsers/pdf/extend/table/CellsExtend.py
doc_parser/dom_parser/parsers/pdf/extend/table/RowExtend.py
bella_domify-0.1.6.8.dist-info/METADATA
bella_domify-0.1.6.8.dist-info/WHEEL
bella_domify-0.1.6.8.dist-info/top_level.txt
bella_domify-0.1.6.8.dist-info/RECORD
