Metadata-Version: 2.4
Name: bella-domify
Version: 0.1.6.8
Summary: An Open source Pdf Parser Python library
Home-page: 
Author: ['tangxiaolong', 'luxu', 'zhangxiaojia']
Author-email: 
License: GPL v3
Keywords: document-doc_parser
Requires-Python: >=3.6
License-File: LICENSE
Requires-Dist: annotated-types==0.6.0
Requires-Dist: anyio==3.7.1
Requires-Dist: boto3==1.34.19
Requires-Dist: botocore==1.34.19
Requires-Dist: certifi==2023.11.17
Requires-Dist: charset-normalizer==3.3.2
Requires-Dist: click==8.1.7
Requires-Dist: distro==1.9.0
Requires-Dist: exceptiongroup==1.2.0
Requires-Dist: fastapi==0.104.1
Requires-Dist: fire==0.5.0
Requires-Dist: fonttools==4.45.1
Requires-Dist: greenlet==3.0.3
Requires-Dist: h11==0.14.0
Requires-Dist: httpcore==1.0.2
Requires-Dist: httpx==0.26.0
Requires-Dist: idna==3.6
Requires-Dist: jellyfish==1.0.3
Requires-Dist: jmespath==1.0.1
Requires-Dist: Levenshtein==0.23.0
Requires-Dist: loguru==0.7.2
Requires-Dist: lxml==4.9.3
Requires-Dist: numpy==1.26.2
Requires-Dist: openai==1.6.1
Requires-Dist: opencv-python==4.8.1.78
Requires-Dist: packaging==23.2
Requires-Dist: pydantic==2.5.2
Requires-Dist: pydantic_core==2.14.5
Requires-Dist: PyMuPDF==1.23.6
Requires-Dist: PyMuPDFb==1.23.6
Requires-Dist: PyMySQL==1.1.0
Requires-Dist: python-dateutil==2.8.2
Requires-Dist: python-docx==1.1.0
Requires-Dist: python-multipart==0.0.6
Requires-Dist: rapidfuzz==3.6.1
Requires-Dist: requests==2.31.0
Requires-Dist: s3transfer==0.10.0
Requires-Dist: six==1.16.0
Requires-Dist: sniffio==1.3.0
Requires-Dist: SQLAlchemy==2.0.25
Requires-Dist: sqlmodel==0.0.16
Requires-Dist: starlette==0.27.0
Requires-Dist: termcolor==2.3.0
Requires-Dist: textdistance==4.6.1
Requires-Dist: tqdm==4.66.1
Requires-Dist: typing_extensions==4.8.0
Requires-Dist: urllib3==1.26.18
Requires-Dist: uvicorn==0.24.0.post1
Requires-Dist: zope.interface==6.1
Requires-Dist: pillow==10.4.0
Requires-Dist: python-pptx==0.6.23
Requires-Dist: python-docx==1.1.0
Requires-Dist: jinja2==3.1.4
Requires-Dist: shapely==2.0.5
Requires-Dist: xlrd==2.0.1
Requires-Dist: confluent-kafka==2.5.0
Requires-Dist: openpyxl==3.1.5
Requires-Dist: pytest==4.6.2
Requires-Dist: tiktoken==0.8.0
Requires-Dist: unoconv==0.9.0
Requires-Dist: bella-openapi==1.0.4
Requires-Dist: chardet==5.2.0
Dynamic: author
Dynamic: description
Dynamic: description-content-type
Dynamic: keywords
Dynamic: license
Dynamic: license-file
Dynamic: requires-dist
Dynamic: requires-python
Dynamic: summary
